tgstorage/__init__.py
tgstorage/api.py
tgstorage/bot.py
tgstorage/config.py
tgstorage/database.py
tgstorage/generate_key.py
tgstorage/index.html
tgstorage/main.py
tgstorage/mime.types
tgstorage/nginx_production.conf
tgstorage_cluster-1.0.2.dist-info/licenses/LICENSE
tgstorage_cluster-1.0.2.dist-info/METADATA
tgstorage_cluster-1.0.2.dist-info/WHEEL
tgstorage_cluster-1.0.2.dist-info/entry_points.txt
tgstorage_cluster-1.0.2.dist-info/top_level.txt
tgstorage_cluster-1.0.2.dist-info/RECORD
