Metadata-Version: 2.4
Name: tgstorage-cluster
Version: 1.0.2
Summary: A lightweight, high-performance file storage API using Telegram as a backend.
Author: DraxonV1
Project-URL: Homepage, https://github.com/DraxonV1/tgstorage
Project-URL: Bug Tracker, https://github.com/DraxonV1/tgstorage/issues
Classifier: Programming Language :: Python :: 3
Classifier: License :: OSI Approved :: MIT License
Classifier: Operating System :: OS Independent
Requires-Python: >=3.10
License-File: LICENSE
Requires-Dist: fastapi
Requires-Dist: uvicorn
Requires-Dist: python-dotenv
Requires-Dist: httpx
Requires-Dist: aiosqlite
Requires-Dist: pydantic
Requires-Dist: pydantic-settings
Requires-Dist: python-telegram-bot
Dynamic: license-file
